xmos_ai_tools/__init__.py
xmos_ai_tools/io_server/__init__.py
xmos_ai_tools/runtime/__init__.py
xmos_ai_tools/runtime/buildfiles/aitoolslib.cmake
xmos_ai_tools/runtime/buildfiles/aitoolslib.make
xmos_ai_tools/runtime/include/fast_flash.h
xmos_ai_tools/runtime/include/flash_server.h
xmos_ai_tools/runtime/include/ioserver.h
xmos_ai_tools/runtime/include/tile_ram_server.h
xmos_ai_tools/runtime/include/flatbuffers/allocator.h
xmos_ai_tools/runtime/include/flatbuffers/array.h
xmos_ai_tools/runtime/include/flatbuffers/base.h
xmos_ai_tools/runtime/include/flatbuffers/bfbs_generator.h
xmos_ai_tools/runtime/include/flatbuffers/buffer.h
xmos_ai_tools/runtime/include/flatbuffers/buffer_ref.h
xmos_ai_tools/runtime/include/flatbuffers/code_generators.h
xmos_ai_tools/runtime/include/flatbuffers/default_allocator.h
xmos_ai_tools/runtime/include/flatbuffers/detached_buffer.h
xmos_ai_tools/runtime/include/flatbuffers/flatbuffer_builder.h
xmos_ai_tools/runtime/include/flatbuffers/flatbuffers.h
xmos_ai_tools/runtime/include/flatbuffers/flatc.h
xmos_ai_tools/runtime/include/flatbuffers/flexbuffers.h
xmos_ai_tools/runtime/include/flatbuffers/grpc.h
xmos_ai_tools/runtime/include/flatbuffers/hash.h
xmos_ai_tools/runtime/include/flatbuffers/idl.h
xmos_ai_tools/runtime/include/flatbuffers/minireflect.h
xmos_ai_tools/runtime/include/flatbuffers/reflection.h
xmos_ai_tools/runtime/include/flatbuffers/reflection_generated.h
xmos_ai_tools/runtime/include/flatbuffers/registry.h
xmos_ai_tools/runtime/include/flatbuffers/stl_emulation.h
xmos_ai_tools/runtime/include/flatbuffers/string.h
xmos_ai_tools/runtime/include/flatbuffers/struct.h
xmos_ai_tools/runtime/include/flatbuffers/table.h
xmos_ai_tools/runtime/include/flatbuffers/util.h
xmos_ai_tools/runtime/include/flatbuffers/vector.h
xmos_ai_tools/runtime/include/flatbuffers/vector_downward.h
xmos_ai_tools/runtime/include/flatbuffers/verifier.h
xmos_ai_tools/runtime/include/flatbuffers/pch/flatc_pch.h
xmos_ai_tools-1.4.2.dist-info/METADATA
xmos_ai_tools-1.4.2.dist-info/WHEEL
xmos_ai_tools-1.4.2.dist-info/top_level.txt
xmos_ai_tools-1.4.2.dist-info/RECORD
